COPYING
MANIFEST.in
README
setup.cfg
setup.py
lava_test/__init__.py
lava_test/commands.py
lava_test/extcmd.py
lava_test/main.py
lava_test/utils.py
lava_test.egg-info/PKG-INFO
lava_test.egg-info/SOURCES.txt
lava_test.egg-info/dependency_links.txt
lava_test.egg-info/entry_points.txt
lava_test.egg-info/not-zip-safe
lava_test.egg-info/requires.txt
lava_test.egg-info/top_level.txt
lava_test/api/__init__.py
lava_test/api/core.py
lava_test/api/delegates.py
lava_test/api/observers.py
lava_test/core/__init__.py
lava_test/core/artifacts.py
lava_test/core/config.py
lava_test/core/hwprofile.py
lava_test/core/installers.py
lava_test/core/loader.py
lava_test/core/parsers.py
lava_test/core/providers.py
lava_test/core/runners.py
lava_test/core/swprofile.py
lava_test/core/tests.py
lava_test/test_definitions/__init__.py
lava_test/test_definitions/bluetooth_enablement.py
lava_test/test_definitions/bootchart.py
lava_test/test_definitions/browser_benchmarks.py
lava_test/test_definitions/device_tree.py
lava_test/test_definitions/e2eaudiotest.py
lava_test/test_definitions/firefox.py
lava_test/test_definitions/gatortests.py
lava_test/test_definitions/glmark2-es2.py
lava_test/test_definitions/glmemperf.py
lava_test/test_definitions/gmpbench.py
lava_test/test_definitions/gtkperf.py
lava_test/test_definitions/insanity.py
lava_test/test_definitions/leb_basic_graphics.py
lava_test/test_definitions/lt_ti_lava.py
lava_test/test_definitions/ltp-snowball-tests.py
lava_test/test_definitions/ltp.py
lava_test/test_definitions/lttng.py
lava_test/test_definitions/peacekeeper.py
lava_test/test_definitions/perf.py
lava_test/test_definitions/posixtestsuite.py
lava_test/test_definitions/pwrmgmt.py
lava_test/test_definitions/pybench.py
lava_test/test_definitions/render-bench.py
lava_test/test_definitions/smem.py
lava_test/test_definitions/spandex-gles2.py
lava_test/test_definitions/stream.py
lava_test/test_definitions/tiobench.py
lava_test/test_definitions/tjbench.py
lava_test/test_definitions/wifi_enablement.py
lava_test/test_definitions/x11perf.py
lava_test/test_definitions/xrestop.py