Metadata-Version: 1.1
Name: lava-test
Version: 0.14
Summary: LAVA test execution framework
Home-page: https://launchpad.net/lava-test
Author: Linaro Validation Team
Author-email: linaro-dev@lists.linaro.org
License: GNU GPLv3
Platform: UNKNOWN
Classifier: Development Status :: 3 - Alpha
Classifier: Intended Audience :: Developers
Classifier: License :: OSI Approved :: GNU General Public License (GPL)
Classifier: Operating System :: OS Independent
Classifier: Programming Language :: Python :: 2.6
Classifier: Topic :: Software Development :: Testing
